README.md
setup.cfg
setup.py
pdp_dswb_python_capabilities/__init__.py
pdp_dswb_python_capabilities/configutil.py
pdp_dswb_python_capabilities/secretutil.py
pdp_dswb_python_capabilities.egg-info/PKG-INFO
pdp_dswb_python_capabilities.egg-info/SOURCES.txt
pdp_dswb_python_capabilities.egg-info/dependency_links.txt
pdp_dswb_python_capabilities.egg-info/requires.txt
pdp_dswb_python_capabilities.egg-info/top_level.txt