Metadata-Version: 2.1
Name: pdp-dswb-python-capabilities
Version: 20.0.5
Summary: A set of lightweight utilities
Home-page: 
Author: johnson
Author-email: 
Classifier: Programming Language :: Python :: 3
Classifier: Operating System :: OS Independent
Requires-Python: >=3.6
